{
  "pinying" : "yang",
  "name" : "羊",
  "data" : {
    "title" : "逐年运势",
    "items" : [
      {
        "value" : "属羊的人逢鼠年，其年正走财运，生意兴隆，事业有进，但年运沾桃花，不病小耗难免；佳运之下，常思厄运，岁末小心谨慎，勿使一年辛苦化东流。若保全年顺畅如意，可在身上戴一块观音菩萨的一佩，定能逢凶化吉。"
      },
      {
        "value" : "属羊的人逢牛年，其年运势起伏，吉凶参半，岁中诸事欠吉，有可能破财消灾，是非口舌常有，家庭不和，万事应以忍为上，以和为贵。一年之中，也可以平平安安，不愁衣食也，若保平安，心中常记忍字。"
      },
      {
        "value" : "属羊的人逢虎年，其年运势上扬，难有阻挡，但须防小人，若不严加防范，纵有佳运，也难保凶多吉少，若羊入虎口，更是死里逃生，在虎年你更应保持勇气和谨慎，千万不要和不三不四的人来往，切忌好色、赌博，最好在身上带一块金属虎牌。"
      },
      {
        "value" : "属羊的人逢兔年，其年运势趋偏财，事业顺遂。诸凡小顺，但也有波折。破财虽无，功名沉浮不定，有意外之灾；口直仗义，取物勿贪。家中若有不快和令人烦恼的事出现，在兔年应该保持冷静出门，打架头殴不要围观。"
      },
      {
        "value" : "属羊的逢龙年，其年正是劫财，忙来忙去一场空，当初奔忙，岁中偶有口舌之灾，但凡凶来，神速星将至；善推机缘，绝处逢生，也有意外惊喜之财，切忌赌博，否则将陷入困境。在龙年你最好安分守己，多拜财神菩萨。"
      },
      {
        "value" : "属羊的人逢蛇年，其年正走正印，事得其成；骑马奔命，凡谋必就，诸事如意，应达之目的，但不可守财失义，否则天意不临，也不会有好报，在蛇年你应多结识贵人和巴结上司，定能升官发财。"
      },
      {
        "value" : "属羊的人逢马年，其年正走偏印，是非中只为功名起，口舌仅为财利生；但否极泰来，人之常运，诸谋迪吉，正事可通，一帆风顺，大吉大利。"
      },
      {
        "value" : "属羊人逢羊年，时及本命，应邮深适之机，文思大进，只恐身心不遂，又见病况，需时时提防头晕失兆，可使一年平安，是年应多拜佛求平安，保健康。"
      },
      {
        "value" : "属羊的人逢猴年，其年运走武印，困顿全消，太阳高照四云有利也；必见门庭之喜气，凡事大通，然不可得意忘形，命里有自当有，命中无莫强求。得意之年应多行善谢佛，增加就蓄。"
      },
      {
        "value" : "属羊人逢鸡年，其年外处多财，宜外出来补，但其年凶多吉少，凡事适可而止，一年太平。"
      },
      {
        "value" : "属羊的人逢狗年，其年劫财流年，生意久隆，不宜外出和做生意，以守为攻是上策；应处处谨慎，万事留意，也有云开见日之时。在家的大门口放一只石狮可得平安。"
      },
      {
        "value" : "属羊的人逢猪年，其年运走伤宫，山人官鬼多，升官无望，交友失利；财神远离，经商艰难，虽有小财但花费九牛二虎之力，在猪年你会有经济和法律方面的麻烦出现，身体也不很好，今年你千万不要冒险，事事应小心谨慎。实事求是，常把老虎图像和在身上也可化凶求吉。多思进取，岁末事有所成。"
      }
    ]
  }
}